{
  "risk_prioritization": {
    "id": "01K6623Q168YSXBDCX5PQPCTEK",
    "prioritization_method": "DREAD",
    "criteria_weights": {
      "business_impact": 0.4,
      "technical_impact": 0.3,
      "likelihood": 0.2,
      "urgency": 0.1
    },
    "prioritized_risks": [
      {
        "risk_id": "01K6623Q168YSXBDCX5PQPCTEK",
        "threat_title": "SQL Injection",
        "risk_score": 9,
        "priority_level": "critical",
        "business_impact": "high",
        "technical_impact": "high",
        "likelihood": "high",
        "urgency": "immediate",
        "mitigation_status": "unmitigated",
        "resource_requirements": "medium",
        "timeline": "short_term",
        "dependencies": [],
        "recommended_actions": [
          "Implement parameterized queries and stored procedures.",
          "Conduct regular security testing."
        ]
      },
      {
        "risk_id": "01K6623Q16YXT0N3EDGJXQQJ51",
        "threat_title": "Cross-Site Scripting (XSS)",
        "risk_score": 8,
        "priority_level": "high",
        "business_impact": "high",
        "technical_impact": "medium",
        "likelihood": "medium",
        "urgency": "short_term",
        "mitigation_status": "unmitigated",
        "resource_requirements": "medium",
        "timeline": "short_term",
        "dependencies": [],
        "recommended_actions": [
          "Use Content Security Policy (CSP) headers.",
          "Sanitize user inputs."
        ]
      },
      {
        "risk_id": "01K6623Q16V3V6KACJ507Y96NZ",
        "threat_title": "Session Hijacking",
        "risk_score": 8,
        "priority_level": "high",
        "business_impact": "medium",
        "technical_impact": "high",
        "likelihood": "medium",
        "urgency": "short_term",
        "mitigation_status": "unmitigated",
        "resource_requirements": "medium",
        "timeline": "short_term",
        "dependencies": [],
        "recommended_actions": [
          "Implement secure session management practices.",
          "Use HTTPS for all communications."
        ]
      },
      {
        "risk_id": "01K6623Q16H60HPV71PQ65WF3W",
        "threat_title": "Insecure Direct Object References (IDOR)",
        "risk_score": 7,
        "priority_level": "high",
        "business_impact": "medium",
        "technical_impact": "medium",
        "likelihood": "medium",
        "urgency": "short_term",
        "mitigation_status": "unmitigated",
        "resource_requirements": "medium",
        "timeline": "short_term",
        "dependencies": [],
        "recommended_actions": [
          "Implement access control checks.",
          "Regularly audit access permissions."
        ]
      },
      {
        "risk_id": "01K6623Q16ZJF808XDZXTTED5A",
        "threat_title": "Denial of Service (DoS)",
        "risk_score": 7,
        "priority_level": "high",
        "business_impact": "high",
        "technical_impact": "medium",
        "likelihood": "medium",
        "urgency": "short_term",
        "mitigation_status": "unmitigated",
        "resource_requirements": "high",
        "timeline": "short_term",
        "dependencies": [],
        "recommended_actions": [
          "Utilize Azure DDoS Protection.",
          "Implement rate limiting."
        ]
      },
      {
        "risk_id": "01K6623Q16NX4Y4MYB9979GS0C",
        "threat_title": "Data Exposure due to Misconfiguration",
        "risk_score": 6,
        "priority_level": "medium",
        "business_impact": "high",
        "technical_impact": "medium",
        "likelihood": "medium",
        "urgency": "short_term",
        "mitigation_status": "unmitigated",
        "resource_requirements": "medium",
        "timeline": "short_term",
        "dependencies": [],
        "recommended_actions": [
          "Regularly review Azure service configurations.",
          "Implement automated configuration checks."
        ]
      },
      {
        "risk_id": "01K6623Q16EBFJ2RDGF7S3HRYE",
        "threat_title": "Weak Authentication Mechanisms",
        "risk_score": 6,
        "priority_level": "medium",
        "business_impact": "high",
        "technical_impact": "medium",
        "likelihood": "medium",
        "urgency": "short_term",
        "mitigation_status": "unmitigated",
        "resource_requirements": "medium",
        "timeline": "short_term",
        "dependencies": [],
        "recommended_actions": [
          "Enforce strong password policies.",
          "Implement multi-factor authentication (MFA)."
        ]
      },
      {
        "risk_id": "01K6623Q162TEKHNKDTK8E52ZH",
        "threat_title": "Insufficient Input Validation",
        "risk_score": 6,
        "priority_level": "medium",
        "business_impact": "medium",
        "technical_impact": "medium",
        "likelihood": "medium",
        "urgency": "short_term",
        "mitigation_status": "unmitigated",
        "resource_requirements": "medium",
        "timeline": "short_term",
        "dependencies": [],
        "recommended_actions": [
          "Implement input validation and sanitization.",
          "Conduct regular security training for developers."
        ]
      }
    ],
    "risk_categories": {
      "critical_risks": [
        "01K6623Q168YSXBDCX5PQPCTEK"
      ],
      "high_priority_risks": [
        "01K6623Q16YXT0N3EDGJXQQJ51",
        "01K6623Q16V3V6KACJ507Y96NZ",
        "01K6623Q16H60HPV71PQ65WF3W",
        "01K6623Q16ZJF808XDZXTTED5A"
      ],
      "medium_priority_risks": [
        "01K6623Q16NX4Y4MYB9979GS0C",
        "01K6623Q16EBFJ2RDGF7S3HRYE",
        "01K6623Q162TEKHNKDTK8E52ZH"
      ],
      "low_priority_risks": []
    },
    "risk_scores": {
      "01K6623Q168YSXBDCX5PQPCTEK": 9.0,
      "01K6623Q16YXT0N3EDGJXQQJ51": 8.0,
      "01K6623Q16V3V6KACJ507Y96NZ": 8.0,
      "01K6623Q16H60HPV71PQ65WF3W": 7.0,
      "01K6623Q16ZJF808XDZXTTED5A": 7.0,
      "01K6623Q16NX4Y4MYB9979GS0C": 6.0,
      "01K6623Q16EBFJ2RDGF7S3HRYE": 6.0,
      "01K6623Q162TEKHNKDTK8E52ZH": 6.0
    },
    "risk_rankings": [
      [
        "01K6623Q168YSXBDCX5PQPCTEK",
        9.0
      ],
      [
        "01K6623Q16YXT0N3EDGJXQQJ51",
        8.0
      ],
      [
        "01K6623Q16V3V6KACJ507Y96NZ",
        8.0
      ],
      [
        "01K6623Q16H60HPV71PQ65WF3W",
        7.0
      ],
      [
        "01K6623Q16ZJF808XDZXTTED5A",
        7.0
      ],
      [
        "01K6623Q16NX4Y4MYB9979GS0C",
        6.0
      ],
      [
        "01K6623Q16EBFJ2RDGF7S3HRYE",
        6.0
      ],
      [
        "01K6623Q162TEKHNKDTK8E52ZH",
        6.0
      ]
    ],
    "business_impact_analysis": {
      "financial_impact": "Potential loss of revenue due to downtime or data breaches.",
      "operational_impact": "Disruption of services leading to loss of user trust.",
      "reputational_impact": "Damage to brand reputation due to security incidents."
    },
    "cost_benefit_analysis": {},
    "mitigation_priorities": [],
    "resource_allocation": {},
    "created_at": "2025-09-27 17:07:23.881333",
    "updated_at": "2025-09-27 17:07:23.881355"
  }
}