{
  "project_name": "Cloud-Based Application on Microsoft Azure",
  "line_of_business": [
    "Web Development",
    "Cloud Computing",
    "Data Management"
  ],
  "application_type": "Web Application",
  "application_audience": "Public",
  "data_sensitivity": "Confidential",
  "authentication_methods": [
    "OAuth",
    "OpenID Connect",
    "Multi-Factor Authentication"
  ],
  "deployment_environment": "Cloud",
  "compliance_requirements": [
    "GDPR",
    "HIPAA",
    "PCI DSS"
  ],
  "security_requirements": [
    "DDoS Protection",
    "Data Encryption in Transit and at Rest",
    "Access Control Management",
    "Incident Response Planning"
  ],
  "business_criticality": "High",
  "threat_modeling_approach": "STRIDE",
  "scope": "Threats related to application components, data processing, and user interactions",
  "assumptions": [
    "Users are external and require secure access",
    "Data stored in Azure SQL Database must be protected",
    "Application hosts sensitive data"
  ],
  "constraints": [
    "Must comply with regulatory requirements",
    "Performance optimization is crucial",
    "Budget limitations for security tools"
  ]
}