{
  "mitigations": [
    {
      "id": "01K5Z7H1ABCD1234567890ABC",
      "description": "Implement Content Security Policy (CSP) to mitigate XSS attacks by restricting the sources of content that can be loaded on the site.",
      "type": "preventive",
      "implementation_status": "proposed",
      "effectiveness": 8,
      "priority": "high",
      "component_id": "01K5Z7H1A3AZVHF3B26JQAP8JC",
      "threat_ids": [
        "01K5Z7H1A3AZVHF3B26JQAP8JC"
      ],
      "implementation_effort": "medium",
      "planned_completion_date": "2025-12-31 00:00:00",
      "actual_completion_date": null,
      "control_category": null,
      "time_to_implement": null,
      "implementation_steps": null,
      "success_metrics": null,
      "dependencies": null,
      "risk_reduction": null,
      "compliance_benefits": null,
      "maintenance_requirements": null,
      "technology_considerations": null,
      "integration_requirements": null,
      "performance_impact": null,
      "scalability_considerations": null,
      "future_proofing": null,
      "defense_in_depth": null,
      "enterprise_considerations": null
    },
    {
      "id": "01K5Z7H1ABCD1234567890DEF",
      "description": "Use prepared statements and parameterized queries in all database interactions to prevent SQL injection.",
      "type": "preventive",
      "implementation_status": "proposed",
      "effectiveness": 9,
      "priority": "critical",
      "component_id": "01K5Z7H1A61425893JMESZKQQC",
      "threat_ids": [
        "01K5Z7H1A61425893JMESZKQQC"
      ],
      "implementation_effort": "high",
      "planned_completion_date": "2025-12-31 00:00:00",
      "actual_completion_date": null,
      "control_category": null,
      "time_to_implement": null,
      "implementation_steps": null,
      "success_metrics": null,
      "dependencies": null,
      "risk_reduction": null,
      "compliance_benefits": null,
      "maintenance_requirements": null,
      "technology_considerations": null,
      "integration_requirements": null,
      "performance_impact": null,
      "scalability_considerations": null,
      "future_proofing": null,
      "defense_in_depth": null,
      "enterprise_considerations": null
    },
    {
      "id": "01K5Z7H1ABCD1234567890GHI",
      "description": "Implement HTTPS for all communications to protect tokens and sensitive data during transmission.",
      "type": "preventive",
      "implementation_status": "proposed",
      "effectiveness": 10,
      "priority": "critical",
      "component_id": "01K5Z7H1A6S274T7ZVAMQKFY48",
      "threat_ids": [
        "01K5Z7H1A6S274T7ZVAMQKFY48",
        "01K5Z7H1A8B05H859Y8HHWETMF"
      ],
      "implementation_effort": "medium",
      "planned_completion_date": "2025-12-31 00:00:00",
      "actual_completion_date": null,
      "control_category": null,
      "time_to_implement": null,
      "implementation_steps": null,
      "success_metrics": null,
      "dependencies": null,
      "risk_reduction": null,
      "compliance_benefits": null,
      "maintenance_requirements": null,
      "technology_considerations": null,
      "integration_requirements": null,
      "performance_impact": null,
      "scalability_considerations": null,
      "future_proofing": null,
      "defense_in_depth": null,
      "enterprise_considerations": null
    },
    {
      "id": "01K5Z7H1ABCD1234567890JKL",
      "description": "Conduct regular security audits and penetration testing to identify and remediate vulnerabilities.",
      "type": "detective",
      "implementation_status": "proposed",
      "effectiveness": 7,
      "priority": "high",
      "component_id": "01K5Z7H1A8B05H859Y8HHWETMF",
      "threat_ids": [
        "01K5Z7H1A8B05H859Y8HHWETMF",
        "01K5Z7H1A8VQQTED1ECD8VJ970"
      ],
      "implementation_effort": "high",
      "planned_completion_date": "2026-03-31 00:00:00",
      "actual_completion_date": null,
      "control_category": null,
      "time_to_implement": null,
      "implementation_steps": null,
      "success_metrics": null,
      "dependencies": null,
      "risk_reduction": null,
      "compliance_benefits": null,
      "maintenance_requirements": null,
      "technology_considerations": null,
      "integration_requirements": null,
      "performance_impact": null,
      "scalability_considerations": null,
      "future_proofing": null,
      "defense_in_depth": null,
      "enterprise_considerations": null
    },
    {
      "id": "01K5Z7H1ABCD1234567890MNO",
      "description": "Implement logging and monitoring for all sensitive actions to detect and respond to unauthorized access attempts.",
      "type": "detective",
      "implementation_status": "proposed",
      "effectiveness": 8,
      "priority": "high",
      "component_id": "01K5Z7H1A8VQQTED1ECD8VJ970",
      "threat_ids": [
        "01K5Z7H1AB2Y24Z93S7BRTBS9N",
        "01K5Z7H1ABCD1234567890JKL"
      ],
      "implementation_effort": "medium",
      "planned_completion_date": "2026-01-31 00:00:00",
      "actual_completion_date": null,
      "control_category": null,
      "time_to_implement": null,
      "implementation_steps": null,
      "success_metrics": null,
      "dependencies": null,
      "risk_reduction": null,
      "compliance_benefits": null,
      "maintenance_requirements": null,
      "technology_considerations": null,
      "integration_requirements": null,
      "performance_impact": null,
      "scalability_considerations": null,
      "future_proofing": null,
      "defense_in_depth": null,
      "enterprise_considerations": null
    },
    {
      "id": "01K5Z7H1ABCD1234567890PQR",
      "description": "Utilize rate limiting and CAPTCHA to mitigate the risk of DoS attacks.",
      "type": "preventive",
      "implementation_status": "proposed",
      "effectiveness": 8,
      "priority": "medium",
      "component_id": "01K5Z7H1A8VQQTED1ECD8VJ970",
      "threat_ids": [
        "01K5Z7H1A8VQQTED1ECD8VJ970"
      ],
      "implementation_effort": "medium",
      "planned_completion_date": "2026-02-28 00:00:00",
      "actual_completion_date": null,
      "control_category": null,
      "time_to_implement": null,
      "implementation_steps": null,
      "success_metrics": null,
      "dependencies": null,
      "risk_reduction": null,
      "compliance_benefits": null,
      "maintenance_requirements": null,
      "technology_considerations": null,
      "integration_requirements": null,
      "performance_impact": null,
      "scalability_considerations": null,
      "future_proofing": null,
      "defense_in_depth": null,
      "enterprise_considerations": null
    },
    {
      "id": "01K5Z7H1ABCD1234567890STU",
      "description": "Educate users about secure session management practices, including the dangers of session fixation.",
      "type": "awareness",
      "implementation_status": "proposed",
      "effectiveness": 6,
      "priority": "medium",
      "component_id": "01K5Z7H1AAZJ8DHFMHK3Z4WT2E",
      "threat_ids": [
        "01K5Z7H1AAXP9A8T6CPE3ZJYDJ"
      ],
      "implementation_effort": "low",
      "planned_completion_date": "2026-01-15 00:00:00",
      "actual_completion_date": null,
      "control_category": null,
      "time_to_implement": null,
      "implementation_steps": null,
      "success_metrics": null,
      "dependencies": null,
      "risk_reduction": null,
      "compliance_benefits": null,
      "maintenance_requirements": null,
      "technology_considerations": null,
      "integration_requirements": null,
      "performance_impact": null,
      "scalability_considerations": null,
      "future_proofing": null,
      "defense_in_depth": null,
      "enterprise_considerations": null
    },
    {
      "id": "01K5Z7H1ABCD1234567890VWX",
      "description": "Implement proper access controls and validation to prevent IDOR vulnerabilities.",
      "type": "preventive",
      "implementation_status": "proposed",
      "effectiveness": 9,
      "priority": "critical",
      "component_id": "01K5Z7H1AAZJ8DHFMHK3Z4WT2E",
      "threat_ids": [
        "01K5Z7H1AAZJ8DHFMHK3Z4WT2E"
      ],
      "implementation_effort": "high",
      "planned_completion_date": "2026-03-31 00:00:00",
      "actual_completion_date": null,
      "control_category": null,
      "time_to_implement": null,
      "implementation_steps": null,
      "success_metrics": null,
      "dependencies": null,
      "risk_reduction": null,
      "compliance_benefits": null,
      "maintenance_requirements": null,
      "technology_considerations": null,
      "integration_requirements": null,
      "performance_impact": null,
      "scalability_considerations": null,
      "future_proofing": null,
      "defense_in_depth": null,
      "enterprise_considerations": null
    },
    {
      "id": "01K5Z7H1ABCD1234567890YZA",
      "description": "Ensure all third-party libraries are regularly updated to mitigate vulnerabilities.",
      "type": "preventive",
      "implementation_status": "proposed",
      "effectiveness": 8,
      "priority": "high",
      "component_id": "01K5Z7H1ABFSPJ7X1DA4NJ6J4P",
      "threat_ids": [
        "01K5Z7H1ABFSPJ7X1DA4NJ6J4P"
      ],
      "implementation_effort": "medium",
      "planned_completion_date": "2026-02-15 00:00:00",
      "actual_completion_date": null,
      "control_category": null,
      "time_to_implement": null,
      "implementation_steps": null,
      "success_metrics": null,
      "dependencies": null,
      "risk_reduction": null,
      "compliance_benefits": null,
      "maintenance_requirements": null,
      "technology_considerations": null,
      "integration_requirements": null,
      "performance_impact": null,
      "scalability_considerations": null,
      "future_proofing": null,
      "defense_in_depth": null,
      "enterprise_considerations": null
    },
    {
      "id": "01K5Z7H1ABCD1234567890BCD",
      "description": "Implement strong encryption for sensitive data both at rest and in transit.",
      "type": "preventive",
      "implementation_status": "proposed",
      "effectiveness": 9,
      "priority": "critical",
      "component_id": "01K5Z7H1A8B05H859Y8HHWETMF",
      "threat_ids": [
        "01K5Z7H1A8B05H859Y8HHWETMF",
        "01K5Z7H1A8VQQTED1ECD8VJ970"
      ],
      "implementation_effort": "high",
      "planned_completion_date": "2026-04-30 00:00:00",
      "actual_completion_date": null,
      "control_category": null,
      "time_to_implement": null,
      "implementation_steps": null,
      "success_metrics": null,
      "dependencies": null,
      "risk_reduction": null,
      "compliance_benefits": null,
      "maintenance_requirements": null,
      "technology_considerations": null,
      "integration_requirements": null,
      "performance_impact": null,
      "scalability_considerations": null,
      "future_proofing": null,
      "defense_in_depth": null,
      "enterprise_considerations": null
    }
  ],
  "mitigation_prioritization": null,
  "enterprise_mitigation_framework": null,
  "summary": "The proposed mitigations address multiple threats identified in the threat model for the default-github project. Each mitigation includes specific implementation guidance, prioritization based on risk, and effectiveness ratings to ensure a comprehensive defense-in-depth strategy. The focus is on preventive measures, with additional detective and awareness strategies to enhance overall security posture."
}